hiclass/BinaryPolicy.py
hiclass/ConstantClassifier.py
hiclass/FlatClassifier.py
hiclass/HierarchicalClassifier.py
hiclass/LocalClassifierPerLevel.py
hiclass/LocalClassifierPerNode.py
hiclass/LocalClassifierPerParentNode.py
hiclass/Pipeline.py
hiclass/__init__.py
hiclass/_hiclass_utils.py
hiclass/_version.py
hiclass/datasets.py
hiclass/metrics.py
hiclass/_calibration/BetaCalibrator.py
hiclass/_calibration/BinaryCalibrator.py
hiclass/_calibration/Calibrator.py
hiclass/_calibration/IsotonicRegression.py
hiclass/_calibration/PlattScaling.py
hiclass/_calibration/VennAbersCalibrator.py
hiclass/_calibration/__init__.py
hiclass/_calibration/calibration_utils.py
hiclass/probability_combiner/ArithmeticMeanCombiner.py
hiclass/probability_combiner/GeometricMeanCombiner.py
hiclass/probability_combiner/MultiplyCombiner.py
hiclass/probability_combiner/ProbabilityCombiner.py
hiclass/probability_combiner/__init__.py
hiclass-5.0.4.dist-info/LICENSE
hiclass-5.0.4.dist-info/METADATA
hiclass-5.0.4.dist-info/WHEEL
hiclass-5.0.4.dist-info/entry_points.txt
hiclass-5.0.4.dist-info/top_level.txt
hiclass-5.0.4.dist-info/RECORD
