Metadata-Version: 2.2
Name: hiclass
Version: 5.0.4
Summary: Hierarchical Classification Library.
Author: Fabio Malcher Miranda, Niklas Koehnecke
Author-email: fabio.malchermiranda@hpi.de, Niklas.Koehnecke@student.hpi.uni-potsdam.de
License: BSD 3-Clause
Project-URL: Bug Tracker, https://github.com/scikit-learn-contrib/hiclass/issues
Project-URL: Source Code, https://github.com/scikit-learn-contrib/hiclass
Project-URL: Related Software, https://gitlab.com/dacs-hpi
Keywords: hierarchical classification
Classifier: Intended Audience :: Science/Research
Classifier: Intended Audience :: Developers
Classifier: License :: OSI Approved
Classifier: Programming Language :: Python
Classifier: Topic :: Software Development
Classifier: Topic :: Scientific/Engineering
Classifier: Operating System :: Microsoft :: Windows
Classifier: Operating System :: POSIX
Classifier: Operating System :: Unix
Classifier: Operating System :: MacOS
Classifier: Programming Language :: Python :: 3
Classifier: Programming Language :: Python :: 3.9
Classifier: Programming Language :: Python :: 3.10
Classifier: Programming Language :: Python :: 3.11
Classifier: Programming Language :: Python :: 3.12
Classifier: Programming Language :: Python :: Implementation :: CPython
Classifier: Programming Language :: Python :: Implementation :: PyPy
Requires-Python: >=3.9,<3.13
License-File: LICENSE
Requires-Dist: networkx
Requires-Dist: numpy
Requires-Dist: scikit-learn>=1.5
Requires-Dist: scipy
Provides-Extra: ray
Requires-Dist: ray>=1.11.0; extra == "ray"
Provides-Extra: dev
Requires-Dist: flake8; extra == "dev"
Requires-Dist: pytest; extra == "dev"
Requires-Dist: pydocstyle; extra == "dev"
Requires-Dist: pytest-cov==3.0.0; extra == "dev"
Requires-Dist: pyfakefs==5.3.5; extra == "dev"
Requires-Dist: black==24.2.0; extra == "dev"
Requires-Dist: pre-commit==2.20.0; extra == "dev"
Requires-Dist: ray; extra == "dev"
Dynamic: author
Dynamic: author-email
Dynamic: classifier
Dynamic: description
Dynamic: description-content-type
Dynamic: keywords
Dynamic: license
Dynamic: project-url
Dynamic: provides-extra
Dynamic: requires-dist
Dynamic: requires-python
Dynamic: summary
